Metadata-Version: 2.1
Name: behavioural-clusters
Version: 0.0.7
Summary: Create Behavioural clusters with the transaction and GA data
Home-page: UNKNOWN
Author: Shashi Bhushan Singh
Author-email: shashi.bhushansingh@ab-inbev.com
License: UNKNOWN
Platform: UNKNOWN
